README.md
flask_itsyouonline.py
setup.py
flask_itsyouonline.egg-info/PKG-INFO
flask_itsyouonline.egg-info/SOURCES.txt
flask_itsyouonline.egg-info/dependency_links.txt
flask_itsyouonline.egg-info/requires.txt
flask_itsyouonline.egg-info/top_level.txt